dash_slicer/__init__.py
dash_slicer/docs.py
dash_slicer/slicer.py
dash_slicer/utils.py
dash_slicer-0.3.1.data/data/LICENSE
dash_slicer-0.3.1.dist-info/LICENSE
dash_slicer-0.3.1.dist-info/METADATA
dash_slicer-0.3.1.dist-info/WHEEL
dash_slicer-0.3.1.dist-info/top_level.txt
dash_slicer-0.3.1.dist-info/zip-safe
dash_slicer-0.3.1.dist-info/RECORD
