Metadata-Version: 2.1
Name: dash-slicer
Version: 0.3.1
Summary: A volume slicer for Dash
Home-page: https://github.com/plotly/dash-slicer
Author: Plotly
Author-email: almar.klein@gmail.com
License: MIT
Classifier: Development Status :: 3 - Alpha
Classifier: Intended Audience :: Developers
Classifier: License :: OSI Approved :: MIT License
Classifier: Programming Language :: Python :: 3
Classifier: Topic :: Software Development :: Libraries :: Python Modules
Classifier: Topic :: Scientific/Engineering :: Visualization
Classifier: Topic :: Software Development :: User Interfaces
Requires-Python: >=3.6.0
License-File: LICENSE
